flake8_html/__init__.py
flake8_html/plugin.py
flake8_html/images/back.svg
flake8_html/images/file.svg
flake8_html/templates/annotated-source.html
flake8_html/templates/file-report.html
flake8_html/templates/index.html
flake8_html/templates/styles.css
flake8_html-0.4.2.dist-info/AUTHORS.rst
flake8_html-0.4.2.dist-info/LICENSE
flake8_html-0.4.2.dist-info/METADATA
flake8_html-0.4.2.dist-info/WHEEL
flake8_html-0.4.2.dist-info/entry_points.txt
flake8_html-0.4.2.dist-info/top_level.txt
flake8_html-0.4.2.dist-info/RECORD
