Metadata-Version: 2.1
Name: flake8-html
Version: 0.4.2
Summary: Generate HTML reports of flake8 violations
Home-page: https://github.com/lordmauve/flake8-html
Author: Daniel Pope
Author-email: mauve@mauveweb.co.uk
License: Apache Software License 2.0
Keywords: flake8 html
Platform: UNKNOWN
Classifier: Development Status :: 4 - Beta
Classifier: Framework :: Flake8
Classifier: Intended Audience :: Developers
Classifier: License :: OSI Approved :: Apache Software License
Classifier: Natural Language :: English
Classifier: Programming Language :: Python :: 2
Classifier: Programming Language :: Python :: 2.7
Classifier: Programming Language :: Python :: 3
Classifier: Programming Language :: Python :: 3.6
Classifier: Programming Language :: Python :: 3.7
Classifier: Programming Language :: Python :: 3.8
Classifier: Programming Language :: Python :: 3.9
License-File: LICENSE
License-File: AUTHORS.rst
